[
    {
        "name":"hemanth",
        "email":"hemanthkumarrajoli@gmail.com",
        "password":"test1234",
        "passwordConform":"test1234",
        "DateOfBirth":"2001-03-05"
    },
    {
        "name":"jayanth",
        "email":"jayanth01@gmail.com",
        "password":"test1234",
        "passwordConform":"test1234",
        "DateOfBirth":"2002-10-18"
    },
    {
        "name":"Balaji",
        "email":"balajijf5@gmail.com",
        "password":"test1234",
        "passwordConform":"test1234",
        "DateOfBirth":"2002-10-18"
    },
    {
        "name":"pavithra",
        "email":"pavi157@gmail.com",
        "password":"test1234",
        "passwordConform":"test1234",
        "DateOfBirth":"2001-07-15"
    },
    {
        "name":"akhila",
        "email":"akhila21@gmail.com",
        "password":"test1234",
        "passwordConform":"test1234",
        "DateOfBirth":"2001-07-15"
    },
    {
        "name":"yaswanth",
        "email":"pennarayaswanth@gmail.com",
        "password":"test1234",
        "passwordConform":"test1234",
        "DateOfBirth":"2000-08-21"
    },
    {
        "name":"rishitha",
        "email":"rishi184@gmail.com",
        "password":"test1234",
        "passwordConform":"test1234",
        "DateOfBirth":"2002-05-09"
    },
    {
        "name":"Srinidi",
        "email":"sri.ni.di.18@gmail.com",
        "password":"test1234",
        "passwordConform":"test1234",
        "DateOfBirth":"2003-09-15"
    },
    {
        "name":"Karthik",
        "email":"ultimatekarthik19@gmail.com",
        "password":"test1234",
        "passwordConform":"test1234",
        "DateOfBirth":"2001-12-10"
    },
    {
        "name":"Haritha",
        "email":"Harithakumari@gmail.com",
        "password":"test1234",
        "passwordConform":"test1234",
        "DateOfBirth":"1999-10-27"
    },
    {
        "name":"raju",
        "email":"rajukumar@gmail.com",
        "password":"test1234",
        "passwordConform":"test1234",
        "DateOfBirth":"2002-06-24"
    },
    {
        "name":"saikumarreddy",
        "email":"saikumar@gmail.com",
        "password":"test1234",
        "passwordConform":"test1234",
        "DateOfBirth":"2004-04-30"
    },
    {
        "name":"harshini reddy",
        "email":"harshini873@gmail.com",
        "password":"test1234",
        "passwordConform":"test1234",
        "DateOfBirth":"2004-02-29"
    },
    {
        "name":"divakar",
        "email":"depu@gmail.com",
        "password":"test1234",
        "passwordConform":"test1234",
        "DateOfBirth":"2002-01-05"
    },
    {
        "name":"bhoomika ",
        "email":"eslavatbhumi09@gmail.com",
        "password":"test1234",
        "passwordConform":"test1234",
        "DateOfBirth":"2001-06-09"
    },
    {
        "name":"prasad",
        "email":"prasadverababu@gmail.com",
        "password":"test1234",
        "passwordConform":"test1234",
        "DateOfBirth":"2001-08-08"
    },
    {
        "name":"anurag",
        "email":"kitsmeanu@gmail.com",
        "password":"test1234",
        "passwordConform":"test1234",
        "DateOfBirth":"2002-02-22"
    },
    {
        "name":"varun reddy",
        "email":"varundc@gmail.com",
        "password":"test1234",
        "passwordConform":"test1234",
        "DateOfBirth":"2011-03-18"
    }
]